{
 "custom_fields": [
  {
   "_assign": null,
   "_comments": null,
   "_liked_by": null,
   "_user_tags": null,
   "allow_in_quick_entry": 0,
   "allow_on_submit": 0,
   "bold": 0,
   "collapsible": 0,
   "collapsible_depends_on": null,
   "columns": 0,
   "creation": "2024-07-03 14:37:31.853546",
   "default": null,
   "depends_on": null,
   "description": null,
   "docstatus": 0,
   "dt": "Leave Allocation",
   "fetch_from": null,
   "fetch_if_empty": 0,
   "fieldname": "custom_cancel_unused_leave",
   "fieldtype": "Button",
   "hidden": 1,
   "hide_border": 0,
   "hide_days": 0,
   "hide_seconds": 0,
   "idx": 13,
   "ignore_user_permissions": 0,
   "ignore_xss_filter": 0,
   "in_global_search": 0,
   "in_list_view": 0,
   "in_preview": 0,
   "in_standard_filter": 0,
   "insert_after": "custom_add_unused_leave",
   "is_system_generated": 0,
   "is_virtual": 0,
   "label": "Cancel Unused Leave",
   "length": 0,
   "link_filters": null,
   "mandatory_depends_on": null,
   "modified": "2024-07-03 14:37:31.853546",
   "modified_by": "Administrator",
   "module": null,
   "name": "Leave Allocation-custom_cancel_unused_leave",
   "no_copy": 0,
   "non_negative": 0,
   "options": null,
   "owner": "Administrator",
   "permlevel": 0,
   "precision": "",
   "print_hide": 0,
   "print_hide_if_no_value": 0,
   "print_width": null,
   "read_only": 0,
   "read_only_depends_on": null,
   "report_hide": 0,
   "reqd": 0,
   "search_index": 0,
   "show_dashboard": 0,
   "sort_options": 0,
   "translatable": 0,
   "unique": 0,
   "width": null
  },
  {
   "_assign": null,
   "_comments": null,
   "_liked_by": null,
   "_user_tags": null,
   "allow_in_quick_entry": 0,
   "allow_on_submit": 1,
   "bold": 0,
   "collapsible": 0,
   "collapsible_depends_on": null,
   "columns": 0,
   "creation": "2024-07-03 11:30:56.980831",
   "default": null,
   "depends_on": null,
   "description": null,
   "docstatus": 0,
   "dt": "Leave Allocation",
   "fetch_from": null,
   "fetch_if_empty": 0,
   "fieldname": "custom_is_add_unused_leave",
   "fieldtype": "Check",
   "hidden": 1,
   "hide_border": 0,
   "hide_days": 0,
   "hide_seconds": 0,
   "idx": 19,
   "ignore_user_permissions": 0,
   "ignore_xss_filter": 0,
   "in_global_search": 0,
   "in_list_view": 0,
   "in_preview": 0,
   "in_standard_filter": 0,
   "insert_after": "total_leaves_encashed",
   "is_system_generated": 0,
   "is_virtual": 0,
   "label": "Is Add Unused Leave",
   "length": 0,
   "link_filters": null,
   "mandatory_depends_on": null,
   "modified": "2024-07-03 11:30:56.980831",
   "modified_by": "Administrator",
   "module": null,
   "name": "Leave Allocation-custom_is_add_unused_leave",
   "no_copy": 0,
   "non_negative": 0,
   "options": null,
   "owner": "Administrator",
   "permlevel": 0,
   "precision": "",
   "print_hide": 0,
   "print_hide_if_no_value": 0,
   "print_width": null,
   "read_only": 0,
   "read_only_depends_on": null,
   "report_hide": 0,
   "reqd": 0,
   "search_index": 0,
   "show_dashboard": 0,
   "sort_options": 0,
   "translatable": 0,
   "unique": 0,
   "width": null
  },
  {
   "_assign": null,
   "_comments": null,
   "_liked_by": null,
   "_user_tags": null,
   "allow_in_quick_entry": 0,
   "allow_on_submit": 1,
   "bold": 0,
   "collapsible": 0,
   "collapsible_depends_on": null,
   "columns": 0,
   "creation": "2024-07-03 10:32:24.309482",
   "default": null,
   "depends_on": null,
   "description": null,
   "docstatus": 0,
   "dt": "Leave Allocation",
   "fetch_from": null,
   "fetch_if_empty": 0,
   "fieldname": "custom_total_unused_leave",
   "fieldtype": "Float",
   "hidden": 0,
   "hide_border": 0,
   "hide_days": 0,
   "hide_seconds": 0,
   "idx": 14,
   "ignore_user_permissions": 0,
   "ignore_xss_filter": 0,
   "in_global_search": 0,
   "in_list_view": 0,
   "in_preview": 0,
   "in_standard_filter": 0,
   "insert_after": "custom_cancel_unused_leave",
   "is_system_generated": 0,
   "is_virtual": 0,
   "label": "Total Unused Leave",
   "length": 0,
   "link_filters": null,
   "mandatory_depends_on": null,
   "modified": "2024-07-03 10:32:24.309482",
   "modified_by": "Administrator",
   "module": null,
   "name": "Leave Allocation-custom_total_unused_leave",
   "no_copy": 0,
   "non_negative": 0,
   "options": null,
   "owner": "Administrator",
   "permlevel": 0,
   "precision": "",
   "print_hide": 0,
   "print_hide_if_no_value": 0,
   "print_width": null,
   "read_only": 1,
   "read_only_depends_on": null,
   "report_hide": 0,
   "reqd": 0,
   "search_index": 0,
   "show_dashboard": 0,
   "sort_options": 0,
   "translatable": 0,
   "unique": 0,
   "width": null
  },
  {
   "_assign": null,
   "_comments": null,
   "_liked_by": null,
   "_user_tags": null,
   "allow_in_quick_entry": 0,
   "allow_on_submit": 0,
   "bold": 0,
   "collapsible": 0,
   "collapsible_depends_on": null,
   "columns": 0,
   "creation": "2024-07-02 12:24:28.128953",
   "default": null,
   "depends_on": null,
   "description": null,
   "docstatus": 0,
   "dt": "Leave Allocation",
   "fetch_from": null,
   "fetch_if_empty": 0,
   "fieldname": "custom_add_unused_leave",
   "fieldtype": "Button",
   "hidden": 0,
   "hide_border": 0,
   "hide_days": 0,
   "hide_seconds": 0,
   "idx": 12,
   "ignore_user_permissions": 0,
   "ignore_xss_filter": 0,
   "in_global_search": 0,
   "in_list_view": 0,
   "in_preview": 0,
   "in_standard_filter": 0,
   "insert_after": "new_leaves_allocated",
   "is_system_generated": 0,
   "is_virtual": 0,
   "label": "Add Unused Leave",
   "length": 0,
   "link_filters": null,
   "mandatory_depends_on": null,
   "modified": "2024-07-02 12:24:28.128953",
   "modified_by": "Administrator",
   "module": null,
   "name": "Leave Allocation-custom_add_unused_leave",
   "no_copy": 0,
   "non_negative": 0,
   "options": null,
   "owner": "Administrator",
   "permlevel": 0,
   "precision": "",
   "print_hide": 0,
   "print_hide_if_no_value": 0,
   "print_width": null,
   "read_only": 0,
   "read_only_depends_on": null,
   "report_hide": 0,
   "reqd": 0,
   "search_index": 0,
   "show_dashboard": 0,
   "sort_options": 0,
   "translatable": 0,
   "unique": 0,
   "width": null
  }
 ],
 "custom_perms": [],
 "doctype": "Leave Allocation",
 "links": [],
 "property_setters": [
  {
   "_assign": null,
   "_comments": null,
   "_liked_by": null,
   "_user_tags": null,
   "creation": "2024-07-03 14:47:33.154227",
   "default_value": null,
   "doc_type": "Leave Allocation",
   "docstatus": 0,
   "doctype_or_field": "DocType",
   "field_name": null,
   "idx": 0,
   "is_system_generated": 0,
   "modified": "2024-07-03 14:47:33.154227",
   "modified_by": "Administrator",
   "module": null,
   "name": "Leave Allocation-main-field_order",
   "owner": "Administrator",
   "property": "field_order",
   "property_type": "Data",
   "row_name": null,
   "value": "[\"naming_series\", \"employee\", \"employee_name\", \"department\", \"company\", \"column_break1\", \"leave_type\", \"from_date\", \"to_date\", \"section_break_6\", \"new_leaves_allocated\", \"custom_add_unused_leave\", \"custom_cancel_unused_leave\", \"custom_total_unused_leave\", \"carry_forward\", \"unused_leaves\", \"total_leaves_allocated\", \"total_leaves_encashed\", \"custom_is_add_unused_leave\", \"column_break_10\", \"compensatory_request\", \"leave_period\", \"leave_policy\", \"leave_policy_assignment\", \"carry_forwarded_leaves_count\", \"expired\", \"amended_from\", \"notes\", \"description\"]"
  }
 ],
 "sync_on_migrate": 1
}